hdx/scraper/geonode/__init__.py
hdx/scraper/geonode/_version.py
hdx/scraper/geonode/geonodetohdx.py
hdx/scraper/geonode/hdx_geonode.yaml
hdx_scraper_geonode-1.5.6.dist-info/METADATA
hdx_scraper_geonode-1.5.6.dist-info/WHEEL
hdx_scraper_geonode-1.5.6.dist-info/licenses/LICENSE
hdx_scraper_geonode-1.5.6.dist-info/RECORD
