Metadata-Version: 2.4
Name: hdx-scraper-geonode
Version: 1.5.6
Summary: HDX Python generic geonode scraper
Project-URL: Homepage, https://github.com/OCHA-DAP/hdx-scraper-geonode
Author-email: Michael Rans <rans@email.com>
License: MIT
License-File: LICENSE
Keywords: HDX,geonode,scraper
Classifier: Development Status :: 5 - Production/Stable
Classifier: Intended Audience :: Developers
Classifier: License :: OSI Approved :: MIT License
Classifier: Natural Language :: English
Classifier: Operating System :: MacOS
Classifier: Operating System :: Microsoft :: Windows
Classifier: Operating System :: POSIX :: Linux
Classifier: Operating System :: Unix
Classifier: Programming Language :: Python
Classifier: Programming Language :: Python :: 3
Classifier: Programming Language :: Python :: 3 :: Only
Classifier: Programming Language :: Python :: 3.8
Classifier: Programming Language :: Python :: 3.9
Classifier: Programming Language :: Python :: 3.10
Classifier: Programming Language :: Python :: 3.11
Classifier: Programming Language :: Python :: 3.12
Classifier: Topic :: Software Development :: Libraries :: Python Modules
Requires-Python: >=3.8
Requires-Dist: hdx-python-api>=6.5.2
Requires-Dist: hdx-python-country>=3.9.8
Requires-Dist: hdx-python-utilities>=3.9.5
Requires-Dist: python-slugify
Provides-Extra: dev
Requires-Dist: pre-commit; extra == 'dev'
Provides-Extra: docs
Requires-Dist: mkapi; extra == 'docs'
Provides-Extra: test
Requires-Dist: pytest; extra == 'test'
Requires-Dist: pytest-cov; extra == 'test'
